CHANGES.rst
MANIFEST.in
README.rst
bootstrap-buildout.py
buildout.cfg
setup.py
travis.cfg
docs/LICENSE.GPL
docs/LICENSE.rst
src/collective/__init__.py
src/collective.atomrss.egg-info/PKG-INFO
src/collective.atomrss.egg-info/SOURCES.txt
src/collective.atomrss.egg-info/dependency_links.txt
src/collective.atomrss.egg-info/entry_points.txt
src/collective.atomrss.egg-info/namespace_packages.txt
src/collective.atomrss.egg-info/not-zip-safe
src/collective.atomrss.egg-info/requires.txt
src/collective.atomrss.egg-info/top_level.txt
src/collective/atomrss/__init__.py
src/collective/atomrss/adapters.py
src/collective/atomrss/configure.zcml
src/collective/atomrss/interfaces.py
src/collective/atomrss/overrides.zcml
src/collective/atomrss/profile.py
src/collective/atomrss/setuphandlers.py
src/collective/atomrss/testing.py
src/collective/atomrss/testing.zcml
src/collective/atomrss/Extensions/__init__.py
src/collective/atomrss/Extensions/install.py
src/collective/atomrss/browser/__init__.py
src/collective/atomrss/browser/configure.zcml
src/collective/atomrss/browser/templates/atom.xml.pt
src/collective/atomrss/profiles/default/browserlayer.xml
src/collective/atomrss/profiles/default/metadata.xml
src/collective/atomrss/profiles/testing/collective.atomrss.testing.txt
src/collective/atomrss/profiles/testing/metadata.xml
src/collective/atomrss/profiles/testing/properties.xml
src/collective/atomrss/profiles/uninstall/browserlayer.xml
src/collective/atomrss/tests/__init__.py
src/collective/atomrss/tests/test_setup.py