Metadata-Version: 1.1
Name: collective.atomrss
Version: 0.1.13
Summary: Package extends Plone syndication for using Atom RSS by default. It also added some field as events date, contentlead image into rss feed.
Home-page: http://pypi.python.org/pypi/collective.atomrss
Author: BenoÃ®t Suttor
Author-email: bsuttor@imio.be
License: BSD
Keywords: Plone Python Atom RSS
Platform: UNKNOWN
Classifier: Framework :: Plone
Classifier: Programming Language :: Python
